[
  {
    "temperature": 0.05,
    "top1_acc": 0.265,
    "top5_acc": 0.555,
    "balanced_acc": 0.1760979944148261,
    "macro_f1": 0.13420290133338678
  },
  {
    "temperature": 0.08,
    "top1_acc": 0.265,
    "top5_acc": 0.535,
    "balanced_acc": 0.1777481594313278,
    "macro_f1": 0.12787197735540395
  },
  {
    "temperature": 0.1,
    "top1_acc": 0.265,
    "top5_acc": 0.535,
    "balanced_acc": 0.1777481594313278,
    "macro_f1": 0.1280369938570541
  },
  {
    "temperature": 0.12,
    "top1_acc": 0.265,
    "top5_acc": 0.535,
    "balanced_acc": 0.1777481594313278,
    "macro_f1": 0.12866491379190476
  },
  {
    "temperature": 0.15,
    "top1_acc": 0.26,
    "top5_acc": 0.54,
    "balanced_acc": 0.17279766438182284,
    "macro_f1": 0.12206425372589816
  },
  {
    "temperature": 0.2,
    "top1_acc": 0.26,
    "top5_acc": 0.53,
    "balanced_acc": 0.17279766438182284,
    "macro_f1": 0.12218212265564826
  },
  {
    "temperature": 0.3,
    "top1_acc": 0.255,
    "top5_acc": 0.53,
    "balanced_acc": 0.17114749936532117,
    "macro_f1": 0.12081484307054689
  },
  {
    "temperature": 0.5,
    "top1_acc": 0.25,
    "top5_acc": 0.535,
    "balanced_acc": 0.16784716933231789,
    "macro_f1": 0.1150216263862411
  }
]